influx/__init__.py
influx/line_protocol.py
influx_client-1.9.0.dist-info/LICENSE
influx_client-1.9.0.dist-info/METADATA
influx_client-1.9.0.dist-info/WHEEL
influx_client-1.9.0.dist-info/top_level.txt
influx_client-1.9.0.dist-info/RECORD
