Metadata-Version: 2.1
Name: influx-client
Version: 1.9.0
Summary: InfluxDB client
Home-page: https://github.com/AxiomExergy/influx-client/
Author: Jacob Alheid
Author-email: shakefu@gmail.com
License: Apache License v2.0
Project-URL: Bug Tracker, https://github.com/AxiomExergy/influx-client/issues
Project-URL: Documentation, https://github.com/AxiomExergy/influx-client/
Project-URL: Source Code, https://github.com/AxiomExergy/influx-client/
Keywords: influx-client,database,influx,influxdb,client
Platform: any
Classifier: Development Status :: 5 - Production/Stable
Classifier: Intended Audience :: Developers
Classifier: License :: OSI Approved :: Apache Software License
Classifier: Operating System :: OS Independent
Classifier: Programming Language :: Python :: 3.5
Classifier: Programming Language :: Python :: 2.7
Classifier: Topic :: Software Development :: Libraries
Classifier: Topic :: Utilities
Classifier: Topic :: Database
Provides-Extra: test
